prophetable/__init__.py
prophetable/prophetable.py
prophetable-0.1.1.dist-info/LICENSE
prophetable-0.1.1.dist-info/METADATA
prophetable-0.1.1.dist-info/WHEEL
prophetable-0.1.1.dist-info/top_level.txt
prophetable-0.1.1.dist-info/RECORD
