Metadata-Version: 2.1
Name: prophetable
Version: 0.1.1
Summary: Run Prophet forcasting models from config files.
Home-page: https://github.com/jucyai/prophetable
Author: Jiachen Yao
Maintainer: Jiachen Yao
License: MIT
Project-URL: Code, https://github.com/jucyai/prophetable
Project-URL: Issue tracker, https://github.com/jucyai/prophetable/issues
Platform: UNKNOWN
Classifier: Intended Audience :: Developers
Classifier: License :: OSI Approved :: MIT License
Classifier: Operating System :: OS Independent
Classifier: Programming Language :: Python
Classifier: Programming Language :: Python :: 3.6
Classifier: Programming Language :: Python :: 3.7
Classifier: Programming Language :: Python :: 3.8
Requires-Python: >=3.6
Requires-Dist: cython
Requires-Dist: numpy
Requires-Dist: pandas
Requires-Dist: matplotlib
Requires-Dist: pystan
Requires-Dist: fbprophet
Requires-Dist: redis
Requires-Dist: red-panda
